LICENSE
README.md
setup.py
tcjexl/__init__.py
tcjexl/expression_functions.py
tcjexl/jexl.py
tcjexl.egg-info/PKG-INFO
tcjexl.egg-info/SOURCES.txt
tcjexl.egg-info/dependency_links.txt
tcjexl.egg-info/requires.txt
tcjexl.egg-info/top_level.txt
tcjexl/pyjexl/__init__.py
tcjexl/pyjexl/analysis.py
tcjexl/pyjexl/evaluator.py
tcjexl/pyjexl/exceptions.py
tcjexl/pyjexl/jexl.py
tcjexl/pyjexl/operators.py
tcjexl/pyjexl/parser.py