Metadata-Version: 2.1
Name: tcjexl
Version: 0.2.0
Summary: Wrapper of pyjexl with additional set of transformations
Home-page: 
Author: 
Author-email: 
License-File: LICENSE
